coloriran/__init__.py
coloriran-1.0.1.dist-info/LICENSE
coloriran-1.0.1.dist-info/METADATA
coloriran-1.0.1.dist-info/WHEEL
coloriran-1.0.1.dist-info/top_level.txt
coloriran-1.0.1.dist-info/RECORD
